README.rst
setup.py
weir/__init__.py
weir/process.py
weir/zfs.py
weir.egg-info/PKG-INFO
weir.egg-info/SOURCES.txt
weir.egg-info/dependency_links.txt
weir.egg-info/requires.txt
weir.egg-info/top_level.txt