Metadata-Version: 1.1
Name: weir
Version: 0.3.0
Summary: A Python API for ZFS
Home-page: https://bitbucket.org/sjdrake/weir
Author: Stephen Drake
Author-email: steve@synergyconsultingnz.com
License: Common Development and Distribution License (CDDL)
Keywords: zfs
Platform: UNKNOWN
Classifier: Development Status :: 3 - Alpha
Classifier: Intended Audience :: Developers
Classifier: License :: OSI Approved
Classifier: Programming Language :: Python :: 2
Classifier: Programming Language :: Python :: 2.6
Classifier: Programming Language :: Python :: 2.7
Classifier: Programming Language :: Python :: 3
Classifier: Programming Language :: Python :: 3.4
